libraptorq/__init__.py
libraptorq/__main__.py
libraptorq-18.3.0.dist-info/DESCRIPTION.rst
libraptorq-18.3.0.dist-info/METADATA
libraptorq-18.3.0.dist-info/RECORD
libraptorq-18.3.0.dist-info/WHEEL
libraptorq-18.3.0.dist-info/entry_points.txt
libraptorq-18.3.0.dist-info/metadata.json
libraptorq-18.3.0.dist-info/top_level.txt
