Metadata-Version: 2.0
Name: libraptorq
Version: 18.3.0
Summary: Python CFFI bindings for libRaptorQ (RaptorQ RFC6330 FEC implementation).
Home-page: http://github.com/mk-fg/python-libraptorq
Author: Mike Kazantsev
Author-email: mk.fraggod@gmail.com
License: WTFPL
Keywords: fec,forward,error,correction,fountain,code,rateless,erasure,codes,raptor,raptorq,libraptorq,lossy,reliable,encoding,rate,parity,redundancy,reliability
Platform: UNKNOWN
Classifier: Development Status :: 4 - Beta
Classifier: Environment :: Console
Classifier: Environment :: No Input/Output (Daemon)
Classifier: Intended Audience :: Developers
Classifier: Intended Audience :: End Users/Desktop
Classifier: Intended Audience :: Information Technology
Classifier: Intended Audience :: Science/Research
Classifier: Intended Audience :: Telecommunications Industry
Classifier: License :: Public Domain
Classifier: Operating System :: POSIX
Classifier: Operating System :: POSIX :: Linux
Classifier: Programming Language :: Python
Classifier: Programming Language :: Python :: 2.7
Classifier: Programming Language :: Python :: 2 :: Only
Classifier: Topic :: Communications
Classifier: Topic :: Internet
Classifier: Topic :: System :: Archiving
Classifier: Topic :: Utilities
Requires-Dist: cffi
Requires-Dist: setuptools
